soxaikit/DM.py
soxaikit/IO.py
soxaikit/PLOT.py
soxaikit/RING.py
soxaikit/__init__.py
soxaikit-0.0.4.dist-info/METADATA
soxaikit-0.0.4.dist-info/WHEEL
soxaikit-0.0.4.dist-info/entry_points.txt
soxaikit-0.0.4.dist-info/license_files/LICENSE
soxaikit-0.0.4.dist-info/RECORD
