Metadata-Version: 2.1
Name: soxaikit
Version: 0.0.4
Summary: soxai kit for data process
Project-URL: Homepage, https://soxai.co.jp/
Author-email: jiabin <wjbthu@gmail.com>
Classifier: License :: OSI Approved :: MIT License
Classifier: Operating System :: OS Independent
Classifier: Programming Language :: Python :: 3
Requires-Python: >=3.7
